{
  "positions": [
    {
      "name": "Cash [NOK]",
      "ticker": "CASH_NOK",
      "volume": 10000,
      "price": 1,
      "cost": 10000,
      "currency": "NOK",
      "asset": "CASH"
    },
    {
      "name": "MOWI",
      "ticker": "MOWI_OSE",
      "volume": 10,
      "price": 200,
      "cost": 2000,
      "currency": "NOK",
      "asset": "EQUITY"
    },
    {
      "name": "DNB Teknologi A",
      "ticker": "DI_NOTEC_OSE",
      "volume": 10,
      "price": 2700,
      "cost": 27000,
      "currency": "NOK",
      "asset": "FUND"
    },
    {
      "name": "Lyxor Core MSCI World",
      "ticker": "LCUW.DE",
      "volume": 500,
      "price": 10,
      "cost": 50000,
      "currency": "EUR",
      "asset": "INDEX_ETF"
    }
  ]
}
